auralis/__init__.py
auralis/common/__init__.py
auralis/common/utilities.py
auralis/common/definitions/__init__.py
auralis/common/definitions/enhancer.py
auralis/common/definitions/openai.py
auralis/common/definitions/output.py
auralis/common/definitions/requests.py
auralis/common/definitions/scheduler.py
auralis/common/logging/__init__.py
auralis/common/logging/logger.py
auralis/common/metrics/__init__.py
auralis/common/metrics/performance.py
auralis/common/scheduling/__init__.py
auralis/common/scheduling/two_phase_scheduler.py
auralis/core/__init__.py
auralis/core/tts.py
auralis/entrypoints/__init__.py
auralis/entrypoints/oai_server.py
auralis/models/__init__.py
auralis/models/base.py
auralis/models/registry.py
auralis/models/xttsv2/XTTSv2.py
auralis/models/xttsv2/__init__.py
auralis/models/xttsv2/components/__init__.py
auralis/models/xttsv2/components/vllm_mm_gpt.py
auralis/models/xttsv2/components/tts/__init__.py
auralis/models/xttsv2/components/tts/layers/__init__.py
auralis/models/xttsv2/components/tts/layers/xtts/__init__.py
auralis/models/xttsv2/components/tts/layers/xtts/hifigan_decoder.py
auralis/models/xttsv2/components/tts/layers/xtts/latent_encoder.py
auralis/models/xttsv2/components/tts/layers/xtts/perceiver_encoder.py
auralis/models/xttsv2/components/tts/layers/xtts/zh_num2words.py
auralis/models/xttsv2/components/vllm/__init__.py
auralis/models/xttsv2/components/vllm/hidden_state_collector.py
auralis/models/xttsv2/components/vllm/hijack.py
auralis/models/xttsv2/config/__init__.py
auralis/models/xttsv2/config/tokenizer.py
auralis/models/xttsv2/config/xttsv2_config.py
auralis/models/xttsv2/config/xttsv2_gpt_config.py
auralis/models/xttsv2/utils/__init__.py
auralis/models/xttsv2/utils/checkpoint_converter.py
auralis-0.2.8.post2.dist-info/LICENSE
auralis-0.2.8.post2.dist-info/METADATA
auralis-0.2.8.post2.dist-info/WHEEL
auralis-0.2.8.post2.dist-info/entry_points.txt
auralis-0.2.8.post2.dist-info/top_level.txt
auralis-0.2.8.post2.dist-info/RECORD
