Metadata-Version: 2.1
Name: auralis
Version: 0.2.8.post2
Summary: This is a faster implementation for TTS models, to be used in highly async environment
Home-page: https://github.com/astramind.ai/auralis
Author: Marco Lironi
Author-email: marcolironi@astramind.ai
Classifier: Programming Language :: Python :: 3
Requires-Python: >=3.10
License-File: LICENSE
Requires-Dist: aiofiles
Requires-Dist: beautifulsoup4
Requires-Dist: cachetools
Requires-Dist: colorama
Requires-Dist: cutlet
Requires-Dist: EbookLib
Requires-Dist: einops
Requires-Dist: ffmpeg
Requires-Dist: fsspec
Requires-Dist: hangul_romanize
Requires-Dist: huggingface_hub
Requires-Dist: ipython
Requires-Dist: librosa
Requires-Dist: networkx
Requires-Dist: num2words
Requires-Dist: opencc
Requires-Dist: packaging
Requires-Dist: pyloudnorm
Requires-Dist: pytest
Requires-Dist: pypinyin
Requires-Dist: safetensors
Requires-Dist: sounddevice
Requires-Dist: soundfile
Requires-Dist: spacy==3.7.5
Requires-Dist: setuptools
Requires-Dist: safetensors
Requires-Dist: torchaudio
Requires-Dist: tokenizers
Requires-Dist: transformers
Requires-Dist: vllm==0.6.4.post1
Requires-Dist: nvidia-ml-py
Requires-Dist: numpy
Requires-Dist: langid
Provides-Extra: docs
Requires-Dist: mkdocs>=1.4.0; extra == "docs"
Requires-Dist: mkdocs-material>=9.0.0; extra == "docs"
Requires-Dist: mkdocstrings>=0.20.0; extra == "docs"
Requires-Dist: mkdocstrings-python>=1.0.0; extra == "docs"
